asbe/__init__.py
asbe/_modidx.py
asbe/_nbdev.py
asbe/base.py
asbe/core.py
asbe/estimators.py
asbe/helper.py
asbe/models.py
asbe-0.1.4.dist-info/LICENSE
asbe-0.1.4.dist-info/METADATA
asbe-0.1.4.dist-info/WHEEL
asbe-0.1.4.dist-info/entry_points.txt
asbe-0.1.4.dist-info/top_level.txt
asbe-0.1.4.dist-info/RECORD
