Metadata-Version: 2.1
Name: asbe
Version: 0.1.4
Summary: Active Learning for treatment effect estimation
Home-page: https://github.com/puhazoli/asbe/
Author: puhazoli
Author-email: puha.zoli@gmail.com
License: Apache Software License 2.0
Keywords: active learning
Classifier: Development Status :: 3 - Alpha
Classifier: Intended Audience :: Science/Research
Classifier: Natural Language :: English
Classifier: Programming Language :: Python :: 3.10
Classifier: License :: OSI Approved :: Apache Software License
Requires-Python: >=3.10
License-File: LICENSE
Requires-Dist: numpy >=1.20
Requires-Dist: scikit-learn >=1.2
Requires-Dist: pandas >=2.0
Requires-Dist: matplotlib
Requires-Dist: pylift
Requires-Dist: econml
Requires-Dist: scikit-uplift
Requires-Dist: pymc-bart >=0.5.2
Requires-Dist: pymc
Requires-Dist: fastcore
Requires-Dist: xbart
Requires-Dist: gpy
Requires-Dist: pyopenbt
Provides-Extra: dev
